blackchat/__init__.py
blackchat/__main__.py
blackchat/core/__init__.py
blackchat/core/chat_manager.py
blackchat/core/grup.py
blackchat/core/user_manager.py
blackchat/utils/__init__.py
blackchat/utils/node.py
blackchat/utils/notifier.py
blackchat/utils/peers.py
blackchat-0.1.4.dist-info/licenses/LICENSE
blackchat-0.1.4.dist-info/METADATA
blackchat-0.1.4.dist-info/WHEEL
blackchat-0.1.4.dist-info/entry_points.txt
blackchat-0.1.4.dist-info/top_level.txt
blackchat-0.1.4.dist-info/RECORD
