Metadata-Version: 2.4
Name: blackchat
Version: 0.1.4
Summary: A simple offline P2P chat system in Python
Home-page: https://github.com/username/blackchat
Author: Iyaz
Author-email: iyaz@example.com
License: MIT
Classifier: Programming Language :: Python :: 3
Classifier: License :: OSI Approved :: MIT License
Classifier: Operating System :: OS Independent
Requires-Python: >=3.10
License-File: LICENSE
Dynamic: license-file
